{"schedule_id": 40000, "domain_size_set": 0, "schedules": [[{"workloadProfileName": "PUSER_SMALL_MIXMKII_SIS_163_cpu", "workloadProfileOffset": 0, "workloadProfileIndex": 23, "rampUp": 600, "rampDown": 600, "targetFactory": "specj", "offset": 0, "duration": 1086.777211004538, "domainSize": 0}, {"workloadProfileName": "PUSER_SMALL_MIXMKII_SIS_14_cpu", "workloadProfileOffset": 0, "workloadProfileIndex": 14, "rampUp": 600, "rampDown": 600, "targetFactory": "specj", "offset": 900.3772124921014, "duration": 440.4390012880249, "domainSize": 0}, {"workloadProfileName": "PUSER_SMALL_MIXMKII_SIS_167_cpu", "workloadProfileOffset": 0, "workloadProfileIndex": 34, "rampUp": 600, "rampDown": 600, "targetFactory": "specj", "offset": 2022.4906194163975, "duration": 779.5336854789123, "domainSize": 0}, {"workloadProfileName": "PUSER_SMALL_MIXMKII_SIS_21_cpu", "workloadProfileOffset": 0, "workloadProfileIndex": 19, "rampUp": 600, "rampDown": 600, "targetFactory": "specj", "offset": 3352.4568319013706, "duration": 3090.051895392674, "domainSize": 0}, {"workloadProfileName": "PUSER_SMALL_MIXMKII_SIS_125_cpu", "workloadProfileOffset": 0, "workloadProfileIndex": 21, "rampUp": 600, "rampDown": 600, "targetFactory": "specj", "offset": 3871.7671514372073, "duration": 1370.662995456828, "domainSize": 0}], [{"workloadProfileName": "PUSER_MEDIUM_MIXMKII_O2_business_ADDORDER", "workloadProfileOffset": 0, "workloadProfileIndex": 1, "rampUp": 600, "rampDown": 600, "targetFactory": "specj", "offset": 6.577862537214891, "duration": 831.0757794662591, "domainSize": 1}, {"workloadProfileName": "PUSER_SMALL_MIXMKII_SIS_357_cpu", "workloadProfileOffset": 0, "workloadProfileIndex": 54, "rampUp": 600, "rampDown": 600, "targetFactory": "specj", "offset": 1127.7570099482427, "duration": 355.21631386274976, "domainSize": 0}, {"workloadProfileName": "PUSER_MEDIUM_MIXMKII_O2_retail_ADDORDER", "workloadProfileOffset": 0, "workloadProfileIndex": 7, "rampUp": 600, "rampDown": 600, "targetFactory": "specj", "offset": 2452.3608854820923, "duration": 2192.7541822166436, "domainSize": 1}, {"workloadProfileName": "PUSER_SMALL_MIXMKII_SIS_417_cpu", "workloadProfileOffset": 0, "workloadProfileIndex": 59, "rampUp": 600, "rampDown": 600, "targetFactory": "specj", "offset": 3869.412576083575, "duration": 1090.962651528815, "domainSize": 0}, {"workloadProfileName": "PUSER_SMALL_MIXMKII_SIS_335_cpu", "workloadProfileOffset": 0, "workloadProfileIndex": 51, "rampUp": 600, "rampDown": 600, "targetFactory": "specj", "offset": 4769.660602507475, "duration": 154.54342479349452, "domainSize": 0}]]}